Flask_SQLAlchemy_Meiqia-2016.8.1.dist-info/DESCRIPTION.rst
Flask_SQLAlchemy_Meiqia-2016.8.1.dist-info/METADATA
Flask_SQLAlchemy_Meiqia-2016.8.1.dist-info/RECORD
Flask_SQLAlchemy_Meiqia-2016.8.1.dist-info/WHEEL
Flask_SQLAlchemy_Meiqia-2016.8.1.dist-info/metadata.json
Flask_SQLAlchemy_Meiqia-2016.8.1.dist-info/top_level.txt
flask_sqlalchemy/__init__.py
flask_sqlalchemy/_compat.py
