Metadata-Version: 2.0
Name: Flask-SQLAlchemy-Meiqia
Version: 2016.8.1
Summary: Adds SQLAlchemy support to your Flask application
Home-page: http://github.com/Meiqia/flask-sqlalchemy
Author: Phil Howell
Author-email: phil@quae.co.uk
License: BSD
Platform: any
Classifier: Environment :: Web Environment
Classifier: Intended Audience :: Developers
Classifier: License :: OSI Approved :: BSD License
Classifier: Operating System :: OS Independent
Classifier: Topic :: Internet :: WWW/HTTP :: Dynamic Content
Classifier: Topic :: Software Development :: Libraries :: Python Modules
Classifier: Programming Language :: Python
Classifier: Programming Language :: Python :: 2
Classifier: Programming Language :: Python :: 2.6
Classifier: Programming Language :: Python :: 2.7
Classifier: Programming Language :: Python :: 3
Classifier: Programming Language :: Python :: 3.3
Classifier: Programming Language :: Python :: 3.4
Classifier: Programming Language :: Python :: 3.5
Requires-Dist: Flask (>=0.10)
Requires-Dist: SQLAlchemy (>=0.8.0)
